odoo/addons/l10n_th_multicurrency_revaluation_operating_unit/README.rst
odoo/addons/l10n_th_multicurrency_revaluation_operating_unit/__init__.py
odoo/addons/l10n_th_multicurrency_revaluation_operating_unit/__manifest__.py
odoo/addons/l10n_th_multicurrency_revaluation_operating_unit/i18n/l10n_th_multicurrency_revaluation_operating_unit.pot
odoo/addons/l10n_th_multicurrency_revaluation_operating_unit/readme/CONTRIBUTORS.rst
odoo/addons/l10n_th_multicurrency_revaluation_operating_unit/readme/DESCRIPTION.rst
odoo/addons/l10n_th_multicurrency_revaluation_operating_unit/readme/USAGE.rst
odoo/addons/l10n_th_multicurrency_revaluation_operating_unit/static/description/icon.png
odoo/addons/l10n_th_multicurrency_revaluation_operating_unit/static/description/index.html
odoo/addons/l10n_th_multicurrency_revaluation_operating_unit/wizard/__init__.py
odoo/addons/l10n_th_multicurrency_revaluation_operating_unit/wizard/wizard_currency_revaluation.py
odoo_addon_l10n_th_multicurrency_revaluation_operating_unit-15.0.1.0.0.2.dist-info/METADATA
odoo_addon_l10n_th_multicurrency_revaluation_operating_unit-15.0.1.0.0.2.dist-info/WHEEL
odoo_addon_l10n_th_multicurrency_revaluation_operating_unit-15.0.1.0.0.2.dist-info/top_level.txt
odoo_addon_l10n_th_multicurrency_revaluation_operating_unit-15.0.1.0.0.2.dist-info/RECORD
