Metadata-Version: 2.1
Name: odoo-addon-l10n-th-multicurrency-revaluation-operating-unit
Version: 15.0.1.0.0.2
Summary: Add Operating Unit to Currency Revaluation
Home-page: https://github.com/OCA/l10n-thailand
Author: Ecosoft, Odoo Community Association (OCA)
Author-email: support@odoo-community.org
License: AGPL-3
Platform: UNKNOWN
Classifier: Programming Language :: Python
Classifier: Framework :: Odoo
Classifier: Framework :: Odoo :: 15.0
Classifier: License :: OSI Approved :: GNU Affero General Public License v3
Classifier: Development Status :: 3 - Alpha
Requires-Python: >=3.8
Requires-Dist: odoo-addon-account-operating-unit <15.1dev,>=15.0dev
Requires-Dist: odoo-addon-l10n-th-multicurrency-revaluation <15.1dev,>=15.0dev
Requires-Dist: odoo <15.1dev,>=15.0a
